[
    {
        "description": "Solid wood fireplace surround",
        "price": "\u00a345",
        "location": "Brighton and Hove"
    },
    {
        "description": "Antique & repro. Marble fireplace surrounds",
        "price": "\u00a31,234,567",
        "location": "Hassocks"
    },
    {
        "description": "Iron cast fireplace",
        "price": "\u00a325",
        "location": "Brighton and Hove"
    },
    {
        "description": "Victorian fireplace",
        "price": "\u00a3150",
        "location": "Hassocks"
    },
    {
        "description": "Fire Place and Surround",
        "price": "\u00a350",
        "location": "Eastbourne, East Sussex"
    },
    {
        "description": "Fireplace surround",
        "price": "\u00a3300",
        "location": "Hassocks"
    },
    {
        "description": "Cast iron fireplace",
        "price": "\u00a355",
        "location": "Brighton and Hove"
    },
    {
        "description": "Cast Iron Fireplace Surround",
        "price": "\u00a3200",
        "location": "Brighton and Hove"
    }
]
